marsilea/__init__.py
marsilea/_api.py
marsilea/_deform.py
marsilea/_version.py
marsilea/base.py
marsilea/dataset.py
marsilea/dendrogram.py
marsilea/exceptions.py
marsilea/heatmap.py
marsilea/layers.py
marsilea/layout.py
marsilea/upset.py
marsilea/utils.py
marsilea/plotter/__init__.py
marsilea/plotter/_seaborn.py
marsilea/plotter/_utils.py
marsilea/plotter/arc.py
marsilea/plotter/area.py
marsilea/plotter/bar.py
marsilea/plotter/base.py
marsilea/plotter/bio.py
marsilea/plotter/images.py
marsilea/plotter/mesh.py
marsilea/plotter/range.py
marsilea/plotter/text.py
oncoprinter/__init__.py
oncoprinter/core.py
oncoprinter/preset.py
marsilea-0.5.7.dist-info/METADATA
marsilea-0.5.7.dist-info/WHEEL
marsilea-0.5.7.dist-info/licenses/LICENSE
marsilea-0.5.7.dist-info/RECORD
