Metadata-Version: 2.4
Name: marsilea
Version: 0.5.7
Summary: Declarative creation of composable visualizations
Project-URL: Home, https://github.com/Marsilea-viz/marsilea
Project-URL: Documentation, https://marsilea.readthedocs.io
Author-email: Yimin Zheng <yzheng@cemm.at>, Zhihang Zheng <zhihang.zheng@connect.polyu.hk>
License: The MIT License (MIT)
License-File: LICENSE
Classifier: Framework :: Matplotlib
Classifier: License :: OSI Approved :: MIT License
Classifier: Programming Language :: Python :: 3
Classifier: Topic :: Scientific/Engineering
Classifier: Topic :: Scientific/Engineering :: Visualization
Requires-Python: >=3.8
Requires-Dist: legendkit
Requires-Dist: matplotlib>=3.6
Requires-Dist: numpy
Requires-Dist: pandas[parquet]
Requires-Dist: platformdirs
Requires-Dist: scipy
Requires-Dist: seaborn
